alvoc/__init__.py
alvoc/__main__.py
alvoc/main.py
alvoc/cli/__init__.py
alvoc/cli/common.py
alvoc/cli/constellations.py
alvoc/cli/convert.py
alvoc/cli/main.py
alvoc/core/__init__.py
alvoc/core/amplicons/__init__.py
alvoc/core/amplicons/main.py
alvoc/core/amplicons/visualize.py
alvoc/core/constellations/__init__.py
alvoc/core/constellations/core.py
alvoc/core/constellations/msa.py
alvoc/core/constellations/nextstrain.py
alvoc/core/constellations/old.py
alvoc/core/utils/__init__.py
alvoc/core/utils/convert.py
alvoc/core/utils/logging.py
alvoc/core/utils/old_constellations.py
alvoc/core/utils/parse.py
alvoc/core/utils/precompute.py
alvoc/core/utils/utils.py
alvoc/core/variants/__init__.py
alvoc/core/variants/prepare.py
alvoc/core/variants/lineages/__init__.py
alvoc/core/variants/lineages/main.py
alvoc/core/variants/lineages/regression.py
alvoc/core/variants/lineages/visualize.py
alvoc/core/variants/mutations/__init__.py
alvoc/core/variants/mutations/helpers.py
alvoc/core/variants/mutations/main.py
alvoc/core/variants/mutations/visualize.py
alvoc-0.5.0.dist-info/METADATA
alvoc-0.5.0.dist-info/WHEEL
alvoc-0.5.0.dist-info/entry_points.txt
alvoc-0.5.0.dist-info/licenses/LICENSE
alvoc-0.5.0.dist-info/RECORD
