Metadata-Version: 2.4
Name: alvoc
Version: 0.5.0
Author-email: mshunjan <manjothunjan@gmail.com>
License-File: LICENSE
Requires-Python: <3.13,>=3.11
Requires-Dist: biopython<2.0,>=1.84
Requires-Dist: matplotlib<4.0.0,>=3.9.0
Requires-Dist: numpy<3.0.0,>=2.0.0
Requires-Dist: ortools<10.0.0,>=9.10.4067
Requires-Dist: pysam<1.0.0,>=0.22.1
Requires-Dist: requests>=2.32.3
Requires-Dist: scikit-learn<2.0.0,>=1.5.1
Requires-Dist: seaborn<1.0.0,>=0.13.2
Requires-Dist: typer<1.0.0,>=0.12.3
